Baidauri/__init__.py
Baidauri/example.py
Baidauri-0.0.1.dist-info/LICENSE.txt
Baidauri-0.0.1.dist-info/METADATA
Baidauri-0.0.1.dist-info/WHEEL
Baidauri-0.0.1.dist-info/top_level.txt
Baidauri-0.0.1.dist-info/RECORD
