Metadata-Version: 2.1
Name: Baidauri
Version: 0.0.1
Summary: test project
Author: ninobaidauri
Author-email: nino.baidauri.1@btu.edu.ge
Classifier: Programming Language :: Python :: 3
Classifier: License :: OSI Approved :: MIT License
Classifier: Operating System :: OS Independent
Requires-Python: >=3.6
License-File: LICENSE.txt
